{
  "id": "R001040",
  "title": "Inspect power mirror switch",
  "category": "service",
  "packageKind": "RIN",
  "packageKindName": "Removal / Installation",
  "section": "body",
  "sectionCode": "J",
  "subsection": "mirror",
  "system": "Power Mirror",
  "subtitle": "",
  "dgName": "",
  "models": [
    "JH1",
    "JH2"
  ],
  "assetDir": "assets/R001040",
  "assets": [
    "1040_3.0_jpn_11037283_3.0_disp.png",
    "1040_3.0_jpn_11037284_3.0_disp.png",
    "1040_3.0_jpn_11287965_3.0_disp.png"
  ],
  "crossRefs": [
    {
      "id": "R000720",
      "label": "Driver Door Power Window Switch Panel Removal",
      "resolved": true
    }
  ],
  "blocks": [
    {
      "type": "heading",
      "level": 1,
      "text": "Inspect power mirror switch"
    },
    {
      "type": "heading",
      "level": 3,
      "text": "1. Driver Door Power Window Switch Panel Removal",
      "refs": [
        {
          "id": "R000720",
          "label": "Driver Door Power Window Switch Panel Removal",
          "resolved": true
        }
      ]
    },
    {
      "type": "heading",
      "level": 3,
      "text": "2. Power mirror switch Check"
    },
    {
      "type": "figure",
      "asset": "1040_3.0_jpn_11287965_3.0_disp.png"
    },
    {
      "type": "figure",
      "asset": "1040_3.0_jpn_11037283_3.0_disp.png"
    },
    {
      "type": "figure",
      "asset": "1040_3.0_jpn_11037284_3.0_disp.png"
    },
    {
      "type": "step",
      "number": "1",
      "text": "Inspect the continuity between terminals in each position of the coupler (A) and confirm that there is continuity only between ○ and ○."
    },
    {
      "type": "heading",
      "level": 3,
      "text": "3. Installation Precautions"
    },
    {
      "type": "step",
      "number": "1",
      "text": "Installation is the reverse of the removal procedure."
    }
  ],
  "source": "sm_contents/60T6GD00_2014_jpn_RIN_20131015114331/Contents/jpn/60T6GD00_2014/RIN/SCT/SC/SYS/R001040_jpn/web/html/R001040_jpn_Content.html",
  "inOutline": true
}