{
  "id": "R002921",
  "title": "Inspect front brake pads.",
  "category": "service",
  "packageKind": "RIN",
  "packageKindName": "Removal / Installation",
  "section": "",
  "sectionCode": "",
  "subsection": "",
  "system": "",
  "subtitle": "",
  "dgName": "",
  "models": [
    "JH1",
    "JH2"
  ],
  "assetDir": "assets/R002921",
  "assets": [
    "2921_3.0_jpn_11589036_2.0_disp.png",
    "2921_3.0_jpn_11589037_2.0_disp.png",
    "2921_3.0_jpn_11589038_2.0_disp.png"
  ],
  "crossRefs": [
    {
      "id": "G000319",
      "label": "Lift Set",
      "resolved": true
    },
    {
      "id": "R000659",
      "label": "Front wheel removal",
      "resolved": true
    }
  ],
  "blocks": [
    {
      "type": "heading",
      "level": 1,
      "text": "Inspect front brake pads."
    },
    {
      "type": "heading",
      "level": 3,
      "text": "1. Lift Set",
      "refs": [
        {
          "id": "G000319",
          "label": "Lift Set",
          "resolved": true
        }
      ]
    },
    {
      "type": "heading",
      "level": 3,
      "text": "2. Front wheel removal",
      "refs": [
        {
          "id": "R000659",
          "label": "Front wheel removal",
          "resolved": true
        }
      ]
    },
    {
      "type": "heading",
      "level": 3,
      "text": "3. Brake pad thickness inspection"
    },
    {
      "type": "figure",
      "asset": "2921_3.0_jpn_11589036_2.0_disp.png"
    },
    {
      "type": "figure",
      "asset": "2921_3.0_jpn_11589037_2.0_disp.png"
    },
    {
      "type": "figure",
      "asset": "2921_3.0_jpn_11589038_2.0_disp.png"
    },
    {
      "type": "step",
      "number": "1",
      "text": "Inspect the thickness (C) of the inner pad (A) and outer pad (B). The backing plate is not included in the thickness. If it is below the use limit value, replace the inner and outer pads as a set."
    },
    {
      "type": "table",
      "rows": [
        [
          {
            "text": "Pad thickness",
            "colspan": 4
          }
        ],
        [
          {
            "text": ""
          },
          {
            "text": "Std.",
            "colspan": 3
          }
        ],
        [
          {
            "text": "",
            "colspan": 2,
            "rowspan": 2
          },
          {
            "text": "12-inch brake spec. vehicle: 12-inch brake spec. vehicle: 12-inch brake spec. vehicle"
          },
          {
            "text": "8.5mm"
          }
        ],
        [
          {
            "text": "13\" brake spec. car:."
          },
          {
            "text": "9.5mm"
          }
        ],
        [
          {
            "text": ""
          },
          {
            "text": "Limit value: 1",
            "colspan": 2
          },
          {
            "text": "1.6mm"
          }
        ]
      ]
    },
    {
      "type": "heading",
      "level": 3,
      "text": "4. Front wheel mounting",
      "refs": [
        {
          "id": "R000659",
          "label": "Front wheel mounting",
          "resolved": true
        }
      ]
    }
  ],
  "source": "sm_contents/60T6GD00_2014_jpn_RIN_20131120133233/Contents/jpn/60T6GD00_2014/RIN/SCT/SC/SYS/R002921_jpn/web/html/R002921_jpn_Content.html",
  "inOutline": false
}