{
  "id": "T986179",
  "title": "Brake pedal does not release the set speed when cruise is in progress",
  "category": "service",
  "packageKind": "TRS",
  "packageKindName": "Troubleshooting",
  "section": "Driver assistance SRS airbags seat belts",
  "sectionCode": "H",
  "subsection": "Speed/body control",
  "system": "Cruise control system",
  "subtitle": "",
  "dgName": "",
  "models": [
    "JH1",
    "JH2"
  ],
  "assetDir": "assets/T986179",
  "assets": [],
  "crossRefs": [
    {
      "id": "T002547",
      "label": "Check DTC",
      "resolved": true
    },
    {
      "id": "R000683",
      "label": "Inspect cruise brake switch",
      "resolved": true
    },
    {
      "id": "T002198",
      "label": "Cruise control input check",
      "resolved": true
    }
  ],
  "blocks": [
    {
      "type": "heading",
      "level": 1,
      "text": "Brake pedal does not release the set speed when cruise is in progress"
    },
    {
      "type": "paragraph",
      "text": "diagnostic item"
    },
    {
      "type": "list",
      "ordered": true,
      "items": [
        {
          "text": "Inspect No. C32 (7.5A) fuse in fuse box"
        },
        {
          "text": "Check DTC",
          "refs": [
            {
              "id": "T002547",
              "label": "Check DTC",
              "resolved": true
            }
          ]
        },
        {
          "text": "Inspect cruise brake switch",
          "refs": [
            {
              "id": "R000683",
              "label": "Inspect cruise brake switch",
              "resolved": true
            }
          ]
        },
        {
          "text": "Cruise control input check",
          "refs": [
            {
              "id": "T002198",
              "label": "Cruise control input check",
              "resolved": true
            }
          ]
        }
      ]
    },
    {
      "type": "paragraph",
      "text": "related item"
    },
    {
      "type": "paragraph",
      "text": "Short circuit in cord between PGM-FI ECU and cruise brake switch"
    }
  ],
  "source": "sm_contents/60T6GD00_2014_jpn_TRS_20131205175231/Contents/jpn/60T6GD00_2014/TRS/SCT/SC/SYS/T986179_jpn/web/html/T986179_jpn_Content.html",
  "inOutline": true
}